jupyterngsplugin/__init__.py
jupyterngsplugin/databases/__init__.py
jupyterngsplugin/databases/sra.py
jupyterngsplugin/files/__init__.py
jupyterngsplugin/files/fastq/__init__.py
jupyterngsplugin/files/fastq/fastqc.py
jupyterngsplugin/image/__init__.py
jupyterngsplugin/image/pdftobase64.py
jupyterngsplugin/markdown/__init__.py
jupyterngsplugin/markdown/alignment.py
jupyterngsplugin/markdown/chipexo.py
jupyterngsplugin/markdown/chipseq.py
jupyterngsplugin/markdown/fastqc.py
jupyterngsplugin/markdown/phantompeakqualtools.py
jupyterngsplugin/markdown/rseqc.py
jupyterngsplugin/markdown/utils.py
jupyterngsplugin/markdown/rnaseq/__init__.py
jupyterngsplugin/markdown/rnaseq/dga.py
jupyterngsplugin/markdown/rnaseq/go.py
jupyterngsplugin/markdown/rnaseq/quantification.py
jupyterngsplugin/utils/__init__.py
jupyterngsplugin/utils/count_lines.py
jupyterngsplugin/utils/errors.py
jupyterngsplugin/utils/load_content_dict.py
jupyterngsplugin/utils/notebook.py
jupyterngsplugin-0.0.13a3.data/data/README.md
tests/__init__.py
tests/test_jupyter.py
jupyterngsplugin-0.0.13a3.dist-info/LICENSE
jupyterngsplugin-0.0.13a3.dist-info/METADATA
jupyterngsplugin-0.0.13a3.dist-info/WHEEL
jupyterngsplugin-0.0.13a3.dist-info/top_level.txt
jupyterngsplugin-0.0.13a3.dist-info/RECORD
