Metadata-Version: 2.1
Name: jupyterngsplugin
Version: 0.0.13a3
Summary: Jupyter notebook plugin for Bioinformatics NGS data analysis
Home-page: https://gitlab.com/r78v10a07/jupyterngsplugin
Author: Vera Alvarez, Roberto
Author-email: veraalva@ncbi.nlm.nih.gov
Maintainer: Vera Alvarez, Roberto
Maintainer-email: veraalva@ncbi.nlm.nih.gov
License: Public Domain
Project-URL: Documentation, https://gitlab.com/r78v10a07/jupyterngsplugin/issues
Project-URL: Source, https://gitlab.com/r78v10a07/jupyterngsplugin
Project-URL: Tracker, https://gitlab.com/r78v10a07/jupyterngsplugin/issues
Keywords: Jupyter NGS
Platform: UNKNOWN
Classifier: Development Status :: 3 - Alpha
Classifier: Framework :: Jupyter
Classifier: Intended Audience :: Science/Research
Classifier: License :: Public Domain
Classifier: Natural Language :: English
Classifier: Operating System :: Unix
Classifier: Programming Language :: Python :: 2.7
Classifier: Programming Language :: Python :: 3
Classifier: Programming Language :: Python :: 3.3
Classifier: Programming Language :: Python :: 3.4
Classifier: Programming Language :: Python :: 3.5
Classifier: Programming Language :: Python :: 3.6
Classifier: Programming Language :: Python :: 3.7
Classifier: Topic :: Scientific/Engineering :: Bio-Informatics
Requires-Dist: jupyter
Requires-Dist: pandas
Requires-Dist: wand
Requires-Dist: biopython
Requires-Dist: xmltodict
